sc_diff_analysis/__init__.py
sc_diff_analysis/main.py
sc_diff_analysis/utils.py
sc_diff_analysis/analyzer/__init__.py
sc_diff_analysis/analyzer/branch_summary_group_by_branch_diff_analyzer.py
sc_diff_analysis/analyzer/branch_summary_group_by_item_type_diff_analyzer.py
sc_diff_analysis/analyzer/common_summary_diff_analyzer.py
sc_diff_analysis/analyzer/customer_summary_diff_analyzer.py
sc_diff_analysis/analyzer/diff_analyzer.py
sc_diff_analysis/analyzer/loan_detail_summary_diff_analyzer.py
sc_diff_analysis/analyzer/manager_summary_diff_analyzer.py
sc_diff_analysis/analyzer/xinka_summary_diff_analyzer.py
sc_diff_analysis/tests/__init__.py
sc_diff_analysis/tests/merge_tests.py
sc_diff_analysis/tests/sample_config/production-inclusive-balance-detail.yml
sc_diff_analysis/tests/sample_config/production-peak-season.yml
sc_diff_analysis/tests/sample_config/production.yml
sc_diff_analysis-0.0.29.dist-info/LICENSE
sc_diff_analysis-0.0.29.dist-info/METADATA
sc_diff_analysis-0.0.29.dist-info/WHEEL
sc_diff_analysis-0.0.29.dist-info/entry_points.txt
sc_diff_analysis-0.0.29.dist-info/top_level.txt
sc_diff_analysis-0.0.29.dist-info/RECORD
